[
{"iden":"11111111-0000-0000-0000-000000000001","forename":"Carlos","surname":"Correa","position":"3B","secondPosition":"SS","batHand":"R","pitchHand":"R","height":74,"weight":215,"age":31,"country":"PUR","teamID":"HOU","teamNum":1,"growthType":[100,100,100,50,50,25,25,0,0,0,0,0,0,-100,-100,-200,-200,-300,-400,-500,-600,-800,-1000,-1200,-1400,-1600,-1800,-1800,-1800,-1800,-1800],"jerseyNum":1,"appearance":["Head3a","Eyes1a","Hair1a","Beard1f","Eyebrows1a","Nose1a","Mouth1a","Clothes1"],"rating":85,"potential":85,"fielding":82,"fieldingThrowPower":85,"fieldingThrowAcc":84,"baseballIQ":88,"speed":48,"stamina":76,"injuryProneness":45,"batContactR":84,"batContactL":0,"batPower":80,"batVision":84,"batDiscipline":82,"batClutch":86,"batBunt":45,"batBaserunning":52,"pitchVelocity":0,"pitchBreak":0,"pitchControlR":0,"pitchControlL":0,"pitchVariety":0,"pitchConsistency":0,"pitchHoldRunners":0,"pitchClutch":0,"salary":15588330,"length":3,"guarantee":15588330,"eSalary":8750000,"eLength":4,"eGuarantee":8750000,"loyalty":75,"greed":70,"ambition":85,"discipline":85,"majorLeagueServiceWeeks":278,"draftNum":1,"draftSeason":2012},
{"iden":"11111111-0000-0000-0000-000000000002","forename":"Jose","surname":"Altuve","position":"2B","secondPosition":"LF","batHand":"R","pitchHand":"R","height":66,"weight":165,"age":36,"country":"VEN","teamID":"HOU","teamNum":1,"growthType":[100,100,100,50,50,25,25,0,0,0,0,0,0,-100,-100,-200,-200,-300,-400,-500,-600,-800,-1000,-1200,-1400,-1600,-1800,-1800,-1800,-1800,-1800],"jerseyNum":27,"appearance":["Head3a","Eyes1b","Hair2a","Beard1a","Eyebrows1b","Nose1b","Mouth1a","Clothes1"],"rating":82,"potential":82,"fielding":74,"fieldingThrowPower":68,"fieldingThrowAcc":78,"baseballIQ":92,"speed":62,"stamina":72,"injuryProneness":30,"batContactR":88,"batContactL":0,"batPower":76,"batVision":84,"batDiscipline":78,"batClutch":90,"batBunt":55,"batBaserunning":72,"pitchVelocity":0,"pitchBreak":0,"pitchControlR":0,"pitchControlL":0,"pitchVariety":0,"pitchConsistency":0,"pitchHoldRunners":0,"pitchClutch":0,"salary":12500000,"length":4,"guarantee":12500000,"eSalary":0,"eLength":0,"eGuarantee":0,"loyalty":90,"greed":45,"ambition":75,"discipline":90,"majorLeagueServiceWeeks":375,"draftNum":0,"draftSeason":2007},
{"iden":"11111111-0000-0000-0000-000000000003","forename":"Christian","surname":"Walker","position":"1B","secondPosition":"","batHand":"R","pitchHand":"R","height":73,"weight":220,"age":35,"country":"USA","teamID":"HOU","teamNum":1,"growthType":[100,100,100,50,50,25,25,0,0,0,0,0,0,-100,-100,-200,-200,-300,-400,-500,-600,-800,-1000,-1200,-1400,-1600,-1800,-1800,-1800,-1800,-1800],"jerseyNum":32,"appearance":["Head1c","Eyes1c","Hair3a","Beard1f","Eyebrows1a","Nose1c","Mouth1a","Clothes1"],"rating":80,"potential":80,"fielding":90,"fieldingThrowPower":74,"fieldingThrowAcc":80,"baseballIQ":84,"speed":42,"stamina":76,"injuryProneness":25,"batContactR":76,"batContactL":0,"batPower":84,"batVision":76,"batDiscipline":78,"batClutch":78,"batBunt":35,"batBaserunning":45,"pitchVelocity":0,"pitchBreak":0,"pitchControlR":0,"pitchControlL":0,"pitchVariety":0,"pitchConsistency":0,"pitchHoldRunners":0,"pitchClutch":0,"salary":10000000,"length":3,"guarantee":10000000,"eSalary":0,"eLength":0,"eGuarantee":0,"loyalty":75,"greed":55,"ambition":70,"discipline":84,"majorLeagueServiceWeeks":201,"draftNum":130,"draftSeason":2012},
{"iden":"11111111-0000-0000-0000-000000000004","forename":"Yordan","surname":"Alvarez","position":"DH","secondPosition":"LF","batHand":"L","pitchHand":"R","height":76,"weight":225,"age":29,"country":"CUB","teamID":"HOU","teamNum":1,"growthType":[100,100,100,50,50,25,25,0,0,0,0,0,0,-100,-100,-200,-200,-300,-400,-500,-600,-800,-1000,-1200,-1400,-1600,-1800,-1800,-1800,-1800,-1800],"jerseyNum":44,"appearance":["Head3a","Eyes1d","Hair4a","Beard1a","Eyebrows1b","Nose1d","Mouth1a","Clothes1"],"rating":93,"potential":93,"fielding":55,"fieldingThrowPower":60,"fieldingThrowAcc":58,"baseballIQ":84,"speed":38,"stamina":78,"injuryProneness":40,"batContactR":0,"batContactL":92,"batPower":97,"batVision":88,"batDiscipline":88,"batClutch":94,"batBunt":30,"batBaserunning":35,"pitchVelocity":0,"pitchBreak":0,"pitchControlR":0,"pitchControlL":0,"pitchVariety":0,"pitchConsistency":0,"pitchHoldRunners":0,"pitchClutch":0,"salary":9583334,"length":3,"guarantee":9583334,"eSalary":0,"eLength":0,"eGuarantee":0,"loyalty":85,"greed":55,"ambition":85,"discipline":82,"majorLeagueServiceWeeks":173,"draftNum":0,"draftSeason":2016},
{"iden":"22222222-0000-0000-0000-000000000001","forename":"Josh","surname":"Hader","position":"P","secondPosition":"","batHand":"L","pitchHand":"L","height":76,"weight":200,"age":32,"country":"USA","teamID":"HOU","teamNum":1,"growthType":[100,100,100,50,50,25,25,0,0,0,0,0,0,-100,-100,-200,-200,-300,-400,-500,-600,-800,-1000,-1200,-1400,-1600,-1800,-1800,-1800,-1800,-1800],"jerseyNum":71,"appearance":["Head1b","Eyes1a","Hair5a","Beard1f","Eyebrows1a","Nose1a","Mouth1a","Clothes1"],"rating":90,"potential":90,"fielding":72,"fieldingThrowPower":78,"fieldingThrowAcc":76,"baseballIQ":88,"speed":42,"stamina":42,"injuryProneness":25,"batContactR":0,"batContactL":0,"batPower":0,"batVision":0,"batDiscipline":0,"batClutch":0,"batBunt":0,"batBaserunning":0,"pitchVelocity":98,"pitchBreak":88,"pitchControlR":82,"pitchControlL":82,"pitchVariety":78,"pitchConsistency":86,"pitchHoldRunners":76,"pitchClutch":94,"salary":9500000,"length":4,"guarantee":9500000,"eSalary":0,"eLength":0,"eGuarantee":0,"loyalty":75,"greed":60,"ambition":80,"discipline":86,"majorLeagueServiceWeeks":225,"draftNum":582,"draftSeason":2012},
{"iden":"22222222-0000-0000-0000-000000000002","forename":"Tatsuya","surname":"Imai","position":"P","secondPosition":"","batHand":"R","pitchHand":"R","height":71,"weight":180,"age":28,"country":"JPN","teamID":"HOU","teamNum":1,"growthType":[100,100,100,50,50,25,25,0,0,0,0,0,0,-100,-100,-200,-200,-300,-400,-500,-600,-800,-1000,-1200,-1400,-1600,-1800,-1800,-1800,-1800,-1800],"jerseyNum":18,"appearance":["Head2a","Eyes1b","Hair6a","Beard1a","Eyebrows1b","Nose1b","Mouth1a","Clothes1"],"rating":82,"potential":88,"fielding":76,"fieldingThrowPower":76,"fieldingThrowAcc":78,"baseballIQ":84,"speed":42,"stamina":82,"injuryProneness":25,"batContactR":0,"batContactL":0,"batPower":0,"batVision":0,"batDiscipline":0,"batClutch":0,"batBunt":0,"batBaserunning":0,"pitchVelocity":95,"pitchBreak":86,"pitchControlR":84,"pitchControlL":84,"pitchVariety":86,"pitchConsistency":82,"pitchHoldRunners":72,"pitchClutch":80,"salary":9000000,"length":1,"guarantee":9000000,"eSalary":9000000,"eLength":2,"eGuarantee":9000000,"loyalty":70,"greed":60,"ambition":85,"discipline":84,"majorLeagueServiceWeeks":0,"draftNum":0,"draftSeason":2026},
{"iden":"22222222-0000-0000-0000-000000000003","forename":"Cristian","surname":"Javier","position":"P","secondPosition":"","batHand":"R","pitchHand":"R","height":73,"weight":180,"age":29,"country":"DOM","teamID":"HOU","teamNum":1,"growthType":[100,100,100,50,50,25,25,0,0,0,0,0,0,-100,-100,-200,-200,-300,-400,-500,-600,-800,-1000,-1200,-1400,-1600,-1800,-1800,-1800,-1800,-1800],"jerseyNum":53,"appearance":["Head3a","Eyes1c","Hair1a","Beard1f","Eyebrows1a","Nose1c","Mouth1a","Clothes1"],"rating":78,"potential":78,"fielding":74,"fieldingThrowPower":74,"fieldingThrowAcc":76,"baseballIQ":82,"speed":42,"stamina":78,"injuryProneness":45,"batContactR":0,"batContactL":0,"batPower":0,"batVision":0,"batDiscipline":0,"batClutch":0,"batBunt":0,"batBaserunning":0,"pitchVelocity":92,"pitchBreak":82,"pitchControlR":78,"pitchControlL":78,"pitchVariety":84,"pitchConsistency":76,"pitchHoldRunners":74,"pitchClutch":80,"salary":6400000,"length":2,"guarantee":6400000,"eSalary":0,"eLength":0,"eGuarantee":0,"loyalty":75,"greed":55,"ambition":75,"discipline":80,"majorLeagueServiceWeeks":156,"draftNum":0,"draftSeason":2015},
{"iden":"11111111-0000-0000-0000-000000000005","forename":"Isaac","surname":"Paredes","position":"3B","secondPosition":"1B","batHand":"R","pitchHand":"R","height":71,"weight":200,"age":27,"country":"MEX","teamID":"HOU","teamNum":1,"growthType":[100,100,100,50,50,25,25,0,0,0,0,0,0,-100,-100,-200,-200,-300,-400,-500,-600,-800,-1000,-1200,-1400,-1600,-1800,-1800,-1800,-1800,-1800],"jerseyNum":17,"appearance":["Head3a","Eyes1d","Hair2a","Beard1a","Eyebrows1b","Nose1d","Mouth1a","Clothes1"],"rating":80,"potential":82,"fielding":72,"fieldingThrowPower":74,"fieldingThrowAcc":74,"baseballIQ":82,"speed":40,"stamina":76,"injuryProneness":25,"batContactR":78,"batContactL":0,"batPower":84,"batVision":78,"batDiscipline":82,"batClutch":80,"batBunt":35,"batBaserunning":38,"pitchVelocity":0,"pitchBreak":0,"pitchControlR":0,"pitchControlL":0,"pitchVariety":0,"pitchConsistency":0,"pitchHoldRunners":0,"pitchClutch":0,"salary":4675000,"length":1,"guarantee":4675000,"eSalary":6675000,"eLength":1,"eGuarantee":6675000,"loyalty":75,"greed":60,"ambition":78,"discipline":80,"majorLeagueServiceWeeks":128,"draftNum":0,"draftSeason":2015},
{"iden":"11111111-0000-0000-0000-000000000006","forename":"LaMonte","surname":"Wade Jr.","position":"1B","secondPosition":"LF","batHand":"L","pitchHand":"R","height":71,"weight":195,"age":32,"country":"USA","teamID":"HOU","teamNum":1,"growthType":[100,100,100,50,50,25,25,0,0,0,0,0,0,-100,-100,-200,-200,-300,-400,-500,-600,-800,-1000,-1200,-1400,-1600,-1800,-1800,-1800,-1800,-1800],"jerseyNum":38,"appearance":["Head1c","Eyes1a","Hair3a","Beard1f","Eyebrows1a","Nose1a","Mouth1a","Clothes1"],"rating":70,"potential":70,"fielding":68,"fieldingThrowPower":62,"fieldingThrowAcc":68,"baseballIQ":78,"speed":48,"stamina":70,"injuryProneness":35,"batContactR":0,"batContactL":72,"batPower":64,"batVision":76,"batDiscipline":78,"batClutch":72,"batBunt":40,"batBaserunning":48,"pitchVelocity":0,"pitchBreak":0,"pitchControlR":0,"pitchControlL":0,"pitchVariety":0,"pitchConsistency":0,"pitchHoldRunners":0,"pitchClutch":0,"salary":500000,"length":1,"guarantee":500000,"eSalary":0,"eLength":0,"eGuarantee":0,"loyalty":70,"greed":45,"ambition":60,"discipline":76,"majorLeagueServiceWeeks":155,"draftNum":270,"draftSeason":2015},
{"iden":"11111111-0000-0000-0000-000000000007","forename":"Christian","surname":"Vazquez","position":"C","secondPosition":"","batHand":"R","pitchHand":"R","height":70,"weight":210,"age":35,"country":"PUR","teamID":"HOU","teamNum":1,"growthType":[100,100,100,50,50,25,25,0,0,0,0,0,0,-100,-100,-200,-200,-300,-400,-500,-600,-800,-1000,-1200,-1400,-1600,-1800,-1800,-1800,-1800,-1800],"jerseyNum":9,"appearance":["Head3a","Eyes1b","Hair4a","Beard1a","Eyebrows1b","Nose1b","Mouth1a","Clothes1"],"rating":68,"potential":68,"fielding":80,"fieldingThrowPower":74,"fieldingThrowAcc":76,"baseballIQ":84,"speed":28,"stamina":68,"injuryProneness":30,"batContactR":68,"batContactL":0,"batPower":56,"batVision":64,"batDiscipline":60,"batClutch":68,"batBunt":55,"batBaserunning":28,"pitchVelocity":0,"pitchBreak":0,"pitchControlR":0,"pitchControlL":0,"pitchVariety":0,"pitchConsistency":0,"pitchHoldRunners":0,"pitchClutch":0,"salary":500000,"length":1,"guarantee":500000,"eSalary":0,"eLength":0,"eGuarantee":0,"loyalty":80,"greed":45,"ambition":55,"discipline":80,"majorLeagueServiceWeeks":291,"draftNum":280,"draftSeason":2008},
{"iden":"22222222-0000-0000-0000-000000000004","forename":"Bryan","surname":"Abreu","position":"P","secondPosition":"","batHand":"R","pitchHand":"R","height":73,"weight":185,"age":29,"country":"DOM","teamID":"HOU","teamNum":1,"growthType":[100,100,100,50,50,25,25,0,0,0,0,0,0,-100,-100,-200,-200,-300,-400,-500,-600,-800,-1000,-1200,-1400,-1600,-1800,-1800,-1800,-1800,-1800],"jerseyNum":52,"appearance":["Head3a","Eyes1c","Hair5a","Beard1f","Eyebrows1a","Nose1c","Mouth1a","Clothes1"],"rating":85,"potential":85,"fielding":72,"fieldingThrowPower":78,"fieldingThrowAcc":72,"baseballIQ":80,"speed":44,"stamina":40,"injuryProneness":30,"batContactR":0,"batContactL":0,"batPower":0,"batVision":0,"batDiscipline":0,"batClutch":0,"batBunt":0,"batBaserunning":0,"pitchVelocity":97,"pitchBreak":90,"pitchControlR":76,"pitchControlL":76,"pitchVariety":76,"pitchConsistency":80,"pitchHoldRunners":74,"pitchClutch":86,"salary":2925000,"length":1,"guarantee":2925000,"eSalary":0,"eLength":0,"eGuarantee":0,"loyalty":75,"greed":55,"ambition":78,"discipline":78,"majorLeagueServiceWeeks":133,"draftNum":0,"draftSeason":2016},
{"iden":"22222222-0000-0000-0000-000000000005","forename":"Steven","surname":"Okert","position":"P","secondPosition":"","batHand":"L","pitchHand":"L","height":75,"weight":225,"age":35,"country":"USA","teamID":"HOU","teamNum":1,"growthType":[100,100,100,50,50,25,25,0,0,0,0,0,0,-100,-100,-200,-200,-300,-400,-500,-600,-800,-1000,-1200,-1400,-1600,-1800,-1800,-1800,-1800,-1800],"jerseyNum":64,"appearance":["Head1c","Eyes1d","Hair6a","Beard1a","Eyebrows1b","Nose1d","Mouth1a","Clothes1"],"rating":74,"potential":74,"fielding":72,"fieldingThrowPower":72,"fieldingThrowAcc":74,"baseballIQ":80,"speed":36,"stamina":36,"injuryProneness":25,"batContactR":0,"batContactL":0,"batPower":0,"batVision":0,"batDiscipline":0,"batClutch":0,"batBunt":0,"batBaserunning":0,"pitchVelocity":91,"pitchBreak":80,"pitchControlR":74,"pitchControlL":74,"pitchVariety":72,"pitchConsistency":76,"pitchHoldRunners":72,"pitchClutch":76,"salary":1162500,"length":1,"guarantee":1162500,"eSalary":0,"eLength":0,"eGuarantee":0,"loyalty":75,"greed":50,"ambition":65,"discipline":80,"majorLeagueServiceWeeks":143,"draftNum":174,"draftSeason":2014},
{"iden":"22222222-0000-0000-0000-000000000006","forename":"Enyel","surname":"De Los Santos","position":"P","secondPosition":"","batHand":"R","pitchHand":"R","height":74,"weight":200,"age":30,"country":"DOM","teamID":"HOU","teamNum":1,"growthType":[100,100,100,50,50,25,25,0,0,0,0,0,0,-100,-100,-200,-200,-300,-400,-500,-600,-800,-1000,-1200,-1400,-1600,-1800,-1800,-1800,-1800,-1800],"jerseyNum":61,"appearance":["Head3a","Eyes1a","Hair1a","Beard1f","Eyebrows1a","Nose1a","Mouth1a","Clothes1"],"rating":73,"potential":73,"fielding":70,"fieldingThrowPower":76,"fieldingThrowAcc":70,"baseballIQ":76,"speed":40,"stamina":38,"injuryProneness":25,"batContactR":0,"batContactL":0,"batPower":0,"batVision":0,"batDiscipline":0,"batClutch":0,"batBunt":0,"batBaserunning":0,"pitchVelocity":94,"pitchBreak":80,"pitchControlR":72,"pitchControlL":72,"pitchVariety":72,"pitchConsistency":72,"pitchHoldRunners":70,"pitchClutch":74,"salary":800000,"length":1,"guarantee":800000,"eSalary":0,"eLength":0,"eGuarantee":0,"loyalty":75,"greed":50,"ambition":65,"discipline":76,"majorLeagueServiceWeeks":132,"draftNum":0,"draftSeason":2014},
{"iden":"11111111-0000-0000-0000-000000000008","forename":"Jeremy","surname":"Pena","position":"SS","secondPosition":"","batHand":"R","pitchHand":"R","height":72,"weight":182,"age":28,"country":"USA","teamID":"HOU","teamNum":1,"growthType":[100,100,100,50,50,25,25,0,0,0,0,0,0,-100,-100,-200,-200,-300,-400,-500,-600,-800,-1000,-1200,-1400,-1600,-1800,-1800,-1800,-1800,-1800],"jerseyNum":3,"appearance":["Head1b","Eyes1b","Hair2a","Beard1a","Eyebrows1b","Nose1b","Mouth1a","Clothes1"],"rating":82,"potential":84,"fielding":90,"fieldingThrowPower":82,"fieldingThrowAcc":86,"baseballIQ":84,"speed":68,"stamina":78,"injuryProneness":25,"batContactR":78,"batContactL":0,"batPower":68,"batVision":74,"batDiscipline":68,"batClutch":82,"batBunt":50,"batBaserunning":68,"pitchVelocity":0,"pitchBreak":0,"pitchControlR":0,"pitchControlL":0,"pitchVariety":0,"pitchConsistency":0,"pitchHoldRunners":0,"pitchClutch":0,"salary":4737500,"length":1,"guarantee":4737500,"eSalary":0,"eLength":0,"eGuarantee":0,"loyalty":80,"greed":55,"ambition":80,"discipline":82,"majorLeagueServiceWeeks":104,"draftNum":102,"draftSeason":2018},
{"iden":"11111111-0000-0000-0000-000000000009","forename":"Jake","surname":"Meyers","position":"CF","secondPosition":"","batHand":"R","pitchHand":"R","height":71,"weight":190,"age":30,"country":"USA","teamID":"HOU","teamNum":1,"growthType":[100,100,100,50,50,25,25,0,0,0,0,0,0,-100,-100,-200,-200,-300,-400,-500,-600,-800,-1000,-1200,-1400,-1600,-1800,-1800,-1800,-1800,-1800],"jerseyNum":6,"appearance":["Head1c","Eyes1c","Hair3a","Beard1f","Eyebrows1a","Nose1c","Mouth1a","Clothes1"],"rating":76,"potential":76,"fielding":88,"fieldingThrowPower":76,"fieldingThrowAcc":80,"baseballIQ":80,"speed":72,"stamina":76,"injuryProneness":30,"batContactR":74,"batContactL":0,"batPower":62,"batVision":70,"batDiscipline":66,"batClutch":72,"batBunt":50,"batBaserunning":72,"pitchVelocity":0,"pitchBreak":0,"pitchControlR":0,"pitchControlL":0,"pitchVariety":0,"pitchConsistency":0,"pitchHoldRunners":0,"pitchClutch":0,"salary":1775000,"length":1,"guarantee":1775000,"eSalary":0,"eLength":0,"eGuarantee":0,"loyalty":78,"greed":50,"ambition":70,"discipline":78,"majorLeagueServiceWeeks":111,"draftNum":393,"draftSeason":2017},
{"iden":"22222222-0000-0000-0000-000000000007","forename":"Peter","surname":"Lambert","position":"P","secondPosition":"","batHand":"R","pitchHand":"R","height":75,"weight":200,"age":29,"country":"USA","teamID":"HOU","teamNum":1,"growthType":[100,100,100,50,50,25,25,0,0,0,0,0,0,-100,-100,-200,-200,-300,-400,-500,-600,-800,-1000,-1200,-1400,-1600,-1800,-1800,-1800,-1800,-1800],"jerseyNum":48,"appearance":["Head1a","Eyes1d","Hair4a","Beard1a","Eyebrows1b","Nose1d","Mouth1a","Clothes1"],"rating":70,"potential":72,"fielding":72,"fieldingThrowPower":72,"fieldingThrowAcc":74,"baseballIQ":76,"speed":40,"stamina":68,"injuryProneness":35,"batContactR":0,"batContactL":0,"batPower":0,"batVision":0,"batDiscipline":0,"batClutch":0,"batBunt":0,"batBaserunning":0,"pitchVelocity":90,"pitchBreak":76,"pitchControlR":78,"pitchControlL":78,"pitchVariety":76,"pitchConsistency":74,"pitchHoldRunners":72,"pitchClutch":70,"salary":767380,"length":1,"guarantee":767380,"eSalary":0,"eLength":0,"eGuarantee":0,"loyalty":75,"greed":45,"ambition":62,"discipline":78,"majorLeagueServiceWeeks":116,"draftNum":65,"draftSeason":2015},
{"iden":"22222222-0000-0000-0000-000000000008","forename":"Nate","surname":"Pearson","position":"P","secondPosition":"","batHand":"R","pitchHand":"R","height":78,"weight":245,"age":29,"country":"USA","teamID":"HOU","teamNum":1,"growthType":[100,100,100,50,50,25,25,0,0,0,0,0,0,-100,-100,-200,-200,-300,-400,-500,-600,-800,-1000,-1200,-1400,-1600,-1800,-1800,-1800,-1800,-1800],"jerseyNum":47,"appearance":["Head1b","Eyes1a","Hair5a","Beard1f","Eyebrows1a","Nose1a","Mouth1a","Clothes1"],"rating":72,"potential":76,"fielding":68,"fieldingThrowPower":84,"fieldingThrowAcc":66,"baseballIQ":74,"speed":38,"stamina":38,"injuryProneness":50,"batContactR":0,"batContactL":0,"batPower":0,"batVision":0,"batDiscipline":0,"batClutch":0,"batBunt":0,"batBaserunning":0,"pitchVelocity":99,"pitchBreak":78,"pitchControlR":68,"pitchControlL":68,"pitchVariety":68,"pitchConsistency":68,"pitchHoldRunners":66,"pitchClutch":72,"salary":675000,"length":1,"guarantee":675000,"eSalary":0,"eLength":0,"eGuarantee":0,"loyalty":70,"greed":55,"ambition":72,"discipline":70,"majorLeagueServiceWeeks":110,"draftNum":28,"draftSeason":2017},
{"iden":"22222222-0000-0000-0000-000000000009","forename":"Hunter","surname":"Brown","position":"P","secondPosition":"","batHand":"R","pitchHand":"R","height":75,"weight":200,"age":27,"country":"USA","teamID":"HOU","teamNum":1,"growthType":[100,100,100,50,50,25,25,0,0,0,0,0,0,-100,-100,-200,-200,-300,-400,-500,-600,-800,-1000,-1200,-1400,-1600,-1800,-1800,-1800,-1800,-1800],"jerseyNum":58,"appearance":["Head1c","Eyes1b","Hair6a","Beard1a","Eyebrows1b","Nose1b","Mouth1a","Clothes1"],"rating":85,"potential":88,"fielding":78,"fieldingThrowPower":80,"fieldingThrowAcc":78,"baseballIQ":86,"speed":44,"stamina":84,"injuryProneness":20,"batContactR":0,"batContactL":0,"batPower":0,"batVision":0,"batDiscipline":0,"batClutch":0,"batBunt":0,"batBaserunning":0,"pitchVelocity":97,"pitchBreak":88,"pitchControlR":82,"pitchControlL":82,"pitchVariety":86,"pitchConsistency":84,"pitchHoldRunners":78,"pitchClutch":84,"salary":2855000,"length":1,"guarantee":2855000,"eSalary":0,"eLength":0,"eGuarantee":0,"loyalty":80,"greed":55,"ambition":85,"discipline":84,"majorLeagueServiceWeeks":83,"draftNum":166,"draftSeason":2019},
{"iden":"11111111-0000-0000-0000-000000000010","forename":"Yainer","surname":"Diaz","position":"C","secondPosition":"","batHand":"R","pitchHand":"R","height":71,"weight":210,"age":27,"country":"DOM","teamID":"HOU","teamNum":1,"growthType":[100,100,100,50,50,25,25,0,0,0,0,0,0,-100,-100,-200,-200,-300,-400,-500,-600,-800,-1000,-1200,-1400,-1600,-1800,-1800,-1800,-1800,-1800],"jerseyNum":21,"appearance":["Head3a","Eyes1c","Hair1a","Beard1f","Eyebrows1a","Nose1c","Mouth1a","Clothes1"],"rating":79,"potential":82,"fielding":74,"fieldingThrowPower":78,"fieldingThrowAcc":74,"baseballIQ":78,"speed":38,"stamina":76,"injuryProneness":25,"batContactR":80,"batContactL":0,"batPower":78,"batVision":72,"batDiscipline":64,"batClutch":78,"batBunt":40,"batBaserunning":34,"pitchVelocity":0,"pitchBreak":0,"pitchControlR":0,"pitchControlL":0,"pitchVariety":0,"pitchConsistency":0,"pitchHoldRunners":0,"pitchClutch":0,"salary":2250000,"length":1,"guarantee":2250000,"eSalary":0,"eLength":0,"eGuarantee":0,"loyalty":78,"greed":55,"ambition":78,"discipline":76,"majorLeagueServiceWeeks":83,"draftNum":0,"draftSeason":2013},
{"iden":"11111111-0000-0000-0000-000000000011","forename":"Nick","surname":"Allen","position":"SS","secondPosition":"2B","batHand":"R","pitchHand":"R","height":69,"weight":170,"age":27,"country":"USA","teamID":"HOU","teamNum":1,"growthType":[100,100,100,50,50,25,25,0,0,0,0,0,0,-100,-100,-200,-200,-300,-400,-500,-600,-800,-1000,-1200,-1400,-1600,-1800,-1800,-1800,-1800,-1800],"jerseyNum":2,"appearance":["Head1b","Eyes1d","Hair2a","Beard1a","Eyebrows1b","Nose1d","Mouth1a","Clothes1"],"rating":74,"potential":76,"fielding":92,"fieldingThrowPower":76,"fieldingThrowAcc":88,"baseballIQ":82,"speed":64,"stamina":76,"injuryProneness":20,"batContactR":70,"batContactL":0,"batPower":42,"batVision":64,"batDiscipline":60,"batClutch":64,"batBunt":55,"batBaserunning":64,"pitchVelocity":0,"pitchBreak":0,"pitchControlR":0,"pitchControlL":0,"pitchVariety":0,"pitchConsistency":0,"pitchHoldRunners":0,"pitchClutch":0,"salary":700000,"length":1,"guarantee":700000,"eSalary":0,"eLength":0,"eGuarantee":0,"loyalty":78,"greed":45,"ambition":68,"discipline":80,"majorLeagueServiceWeeks":77,"draftNum":114,"draftSeason":2017},
{"iden":"22222222-0000-0000-0000-000000000010","forename":"Hayden","surname":"Wesneski","position":"P","secondPosition":"","batHand":"R","pitchHand":"R","height":75,"weight":210,"age":28,"country":"USA","teamID":"HOU","teamNum":1,"growthType":[100,100,100,50,50,25,25,0,0,0,0,0,0,-100,-100,-200,-200,-300,-400,-500,-600,-800,-1000,-1200,-1400,-1600,-1800,-1800,-1800,-1800,-1800],"jerseyNum":39,"appearance":["Head1c","Eyes1a","Hair3a","Beard1f","Eyebrows1a","Nose1a","Mouth1a","Clothes1"],"rating":73,"potential":76,"fielding":74,"fieldingThrowPower":74,"fieldingThrowAcc":76,"baseballIQ":78,"speed":40,"stamina":70,"injuryProneness":25,"batContactR":0,"batContactL":0,"batPower":0,"batVision":0,"batDiscipline":0,"batClutch":0,"batBunt":0,"batBaserunning":0,"pitchVelocity":93,"pitchBreak":80,"pitchControlR":76,"pitchControlL":76,"pitchVariety":78,"pitchConsistency":74,"pitchHoldRunners":72,"pitchClutch":74,"salary":487500,"length":1,"guarantee":487500,"eSalary":0,"eLength":0,"eGuarantee":0,"loyalty":75,"greed":50,"ambition":70,"discipline":76,"majorLeagueServiceWeeks":78,"draftNum":191,"draftSeason":2019},
{"iden":"22222222-0000-0000-0000-000000000011","forename":"Bennett","surname":"Sousa","position":"P","secondPosition":"","batHand":"L","pitchHand":"L","height":74,"weight":205,"age":31,"country":"USA","teamID":"HOU","teamNum":1,"growthType":[100,100,100,50,50,25,25,0,0,0,0,0,0,-100,-100,-200,-200,-300,-400,-500,-600,-800,-1000,-1200,-1400,-1600,-1800,-1800,-1800,-1800,-1800],"jerseyNum":67,"appearance":["Head1a","Eyes1b","Hair4a","Beard1a","Eyebrows1b","Nose1b","Mouth1a","Clothes1"],"rating":71,"potential":71,"fielding":70,"fieldingThrowPower":70,"fieldingThrowAcc":72,"baseballIQ":76,"speed":38,"stamina":36,"injuryProneness":25,"batContactR":0,"batContactL":0,"batPower":0,"batVision":0,"batDiscipline":0,"batClutch":0,"batBunt":0,"batBaserunning":0,"pitchVelocity":91,"pitchBreak":78,"pitchControlR":72,"pitchControlL":72,"pitchVariety":70,"pitchConsistency":72,"pitchHoldRunners":70,"pitchClutch":72,"salary":455000,"length":1,"guarantee":455000,"eSalary":0,"eLength":0,"eGuarantee":0,"loyalty":75,"greed":45,"ambition":62,"discipline":76,"majorLeagueServiceWeeks":76,"draftNum":0,"draftSeason":2018},
{"iden":"11111111-0000-0000-0000-000000000012","forename":"Taylor","surname":"Trammell","position":"LF","secondPosition":"CF","batHand":"L","pitchHand":"L","height":73,"weight":210,"age":28,"country":"USA","teamID":"HOU","teamNum":1,"growthType":[100,100,100,50,50,25,25,0,0,0,0,0,0,-100,-100,-200,-200,-300,-400,-500,-600,-800,-1000,-1200,-1400,-1600,-1800,-1800,-1800,-1800,-1800],"jerseyNum":12,"appearance":["Head1b","Eyes1c","Hair5a","Beard1f","Eyebrows1a","Nose1c","Mouth1a","Clothes1"],"rating":68,"potential":70,"fielding":74,"fieldingThrowPower":70,"fieldingThrowAcc":68,"baseballIQ":72,"speed":76,"stamina":74,"injuryProneness":30,"batContactR":0,"batContactL":64,"batPower":62,"batVision":64,"batDiscipline":64,"batClutch":64,"batBunt":40,"batBaserunning":76,"pitchVelocity":0,"pitchBreak":0,"pitchControlR":0,"pitchControlL":0,"pitchVariety":0,"pitchConsistency":0,"pitchHoldRunners":0,"pitchClutch":0,"salary":438236,"length":1,"guarantee":438236,"eSalary":0,"eLength":0,"eGuarantee":0,"loyalty":72,"greed":48,"ambition":68,"discipline":72,"majorLeagueServiceWeeks":74,"draftNum":35,"draftSeason":2016},
{"iden":"22222222-0000-0000-0000-000000000012","forename":"Ronel","surname":"Blanco","position":"P","secondPosition":"","batHand":"L","pitchHand":"L","height":74,"weight":195,"age":32,"country":"VEN","teamID":"HOU","teamNum":1,"growthType":[100,100,100,50,50,25,25,0,0,0,0,0,0,-100,-100,-200,-200,-300,-400,-500,-600,-800,-1000,-1200,-1400,-1600,-1800,-1800,-1800,-1800,-1800],"jerseyNum":56,"appearance":["Head3a","Eyes1d","Hair6a","Beard1a","Eyebrows1b","Nose1d","Mouth1a","Clothes1"],"rating":76,"potential":78,"fielding":74,"fieldingThrowPower":74,"fieldingThrowAcc":76,"baseballIQ":78,"speed":40,"stamina":80,"injuryProneness":30,"batContactR":0,"batContactL":0,"batPower":0,"batVision":0,"batDiscipline":0,"batClutch":0,"batBunt":0,"batBaserunning":0,"pitchVelocity":93,"pitchBreak":82,"pitchControlR":76,"pitchControlL":76,"pitchVariety":80,"pitchConsistency":76,"pitchHoldRunners":72,"pitchClutch":78,"salary":401350,"length":1,"guarantee":401350,"eSalary":0,"eLength":0,"eGuarantee":0,"loyalty":78,"greed":50,"ambition":74,"discipline":78,"majorLeagueServiceWeeks":67,"draftNum":0,"draftSeason":2016},
{"iden":"11111111-0000-0000-0000-000000000013","forename":"Cam","surname":"Smith","position":"RF","secondPosition":"","batHand":"R","pitchHand":"R","height":73,"weight":210,"age":23,"country":"USA","teamID":"HOU","teamNum":1,"growthType":[100,100,100,50,50,25,25,0,0,0,0,0,0,-100,-100,-200,-200,-300,-400,-500,-600,-800,-1000,-1200,-1400,-1600,-1800,-1800,-1800,-1800,-1800],"jerseyNum":44,"appearance":["Head1a","Eyes1a","Hair1a","Beard1f","Eyebrows1a","Nose1a","Mouth1a","Clothes1"],"rating":78,"potential":88,"fielding":74,"fieldingThrowPower":82,"fieldingThrowAcc":74,"baseballIQ":78,"speed":54,"stamina":78,"injuryProneness":20,"batContactR":78,"batContactL":0,"batPower":80,"batVision":74,"batDiscipline":72,"batClutch":76,"batBunt":40,"batBaserunning":50,"pitchVelocity":0,"pitchBreak":0,"pitchControlR":0,"pitchControlL":0,"pitchVariety":0,"pitchConsistency":0,"pitchHoldRunners":0,"pitchClutch":0,"salary":404950,"length":1,"guarantee":404950,"eSalary":0,"eLength":0,"eGuarantee":0,"loyalty":75,"greed":55,"ambition":88,"discipline":78,"majorLeagueServiceWeeks":26,"draftNum":14,"draftSeason":2024},
{"iden":"22222222-0000-0000-0000-000000000013","forename":"Bryan","surname":"King","position":"P","secondPosition":"","batHand":"R","pitchHand":"L","height":74,"weight":205,"age":29,"country":"USA","teamID":"HOU","teamNum":1,"growthType":[100,100,100,50,50,25,25,0,0,0,0,0,0,-100,-100,-200,-200,-300,-400,-500,-600,-800,-1000,-1200,-1400,-1600,-1800,-1800,-1800,-1800,-1800],"jerseyNum":63,"appearance":["Head1b","Eyes1b","Hair2a","Beard1a","Eyebrows1b","Nose1b","Mouth1a","Clothes1"],"rating":68,"potential":71,"fielding":68,"fieldingThrowPower":72,"fieldingThrowAcc":70,"baseballIQ":72,"speed":38,"stamina":36,"injuryProneness":25,"batContactR":0,"batContactL":0,"batPower":0,"batVision":0,"batDiscipline":0,"batClutch":0,"batBunt":0,"batBaserunning":0,"pitchVelocity":92,"pitchBreak":76,"pitchControlR":70,"pitchControlL":70,"pitchVariety":68,"pitchConsistency":68,"pitchHoldRunners":68,"pitchClutch":70,"salary":399950,"length":1,"guarantee":399950,"eSalary":0,"eLength":0,"eGuarantee":0,"loyalty":72,"greed":48,"ambition":65,"discipline":72,"majorLeagueServiceWeeks":41,"draftNum":220,"draftSeason":2018},
{"iden":"22222222-0000-0000-0000-000000000014","forename":"Spencer","surname":"Arrighetti","position":"P","secondPosition":"","batHand":"R","pitchHand":"R","height":75,"weight":195,"age":26,"country":"USA","teamID":"HOU","teamNum":1,"growthType":[100,100,100,50,50,25,25,0,0,0,0,0,0,-100,-100,-200,-200,-300,-400,-500,-600,-800,-1000,-1200,-1400,-1600,-1800,-1800,-1800,-1800,-1800],"jerseyNum":34,"appearance":["Head1c","Eyes1c","Hair3a","Beard1f","Eyebrows1a","Nose1c","Mouth1a","Clothes1"],"rating":72,"potential":78,"fielding":72,"fieldingThrowPower":76,"fieldingThrowAcc":72,"baseballIQ":76,"speed":42,"stamina":78,"injuryProneness":30,"batContactR":0,"batContactL":0,"batPower":0,"batVision":0,"batDiscipline":0,"batClutch":0,"batBunt":0,"batBaserunning":0,"pitchVelocity":93,"pitchBreak":82,"pitchControlR":72,"pitchControlL":72,"pitchVariety":80,"pitchConsistency":70,"pitchHoldRunners":70,"pitchClutch":72,"salary":398650,"length":1,"guarantee":398650,"eSalary":0,"eLength":0,"eGuarantee":0,"loyalty":75,"greed":50,"ambition":75,"discipline":74,"majorLeagueServiceWeeks":52,"draftNum":182,"draftSeason":2021},
{"iden":"22222222-0000-0000-0000-000000000015","forename":"Mike","surname":"Burrows","position":"P","secondPosition":"","batHand":"R","pitchHand":"R","height":74,"weight":190,"age":26,"country":"USA","teamID":"HOU","teamNum":1,"growthType":[100,100,100,50,50,25,25,0,0,0,0,0,0,-100,-100,-200,-200,-300,-400,-500,-600,-800,-1000,-1200,-1400,-1600,-1800,-1800,-1800,-1800,-1800],"jerseyNum":45,"appearance":["Head1a","Eyes1d","Hair4a","Beard1a","Eyebrows1b","Nose1d","Mouth1a","Clothes1"],"rating":68,"potential":74,"fielding":70,"fieldingThrowPower":72,"fieldingThrowAcc":70,"baseballIQ":74,"speed":40,"stamina":72,"injuryProneness":30,"batContactR":0,"batContactL":0,"batPower":0,"batVision":0,"batDiscipline":0,"batClutch":0,"batBunt":0,"batBaserunning":0,"pitchVelocity":92,"pitchBreak":78,"pitchControlR":70,"pitchControlL":70,"pitchVariety":76,"pitchConsistency":68,"pitchHoldRunners":68,"pitchClutch":68,"salary":400050,"length":1,"guarantee":400050,"eSalary":0,"eLength":0,"eGuarantee":0,"loyalty":72,"greed":48,"ambition":70,"discipline":72,"majorLeagueServiceWeeks":20,"draftNum":328,"draftSeason":2018},
{"iden":"22222222-0000-0000-0000-000000000016","forename":"Kai-Wei","surname":"Teng","position":"P","secondPosition":"","batHand":"R","pitchHand":"R","height":73,"weight":185,"age":27,"country":"TWN","teamID":"HOU","teamNum":1,"growthType":[100,100,100,50,50,25,25,0,0,0,0,0,0,-100,-100,-200,-200,-300,-400,-500,-600,-800,-1000,-1200,-1400,-1600,-1800,-1800,-1800,-1800,-1800],"jerseyNum":41,"appearance":["Head2a","Eyes1a","Hair5a","Beard1f","Eyebrows1a","Nose1a","Mouth1a","Clothes1"],"rating":66,"potential":78,"fielding":68,"fieldingThrowPower":74,"fieldingThrowAcc":70,"baseballIQ":72,"speed":40,"stamina":68,"injuryProneness":25,"batContactR":0,"batContactL":0,"batPower":0,"batVision":0,"batDiscipline":0,"batClutch":0,"batBunt":0,"batBaserunning":0,"pitchVelocity":91,"pitchBreak":76,"pitchControlR":68,"pitchControlL":68,"pitchVariety":74,"pitchConsistency":66,"pitchHoldRunners":64,"pitchClutch":66,"salary":393350,"length":1,"guarantee":393350,"eSalary":0,"eLength":0,"eGuarantee":0,"loyalty":70,"greed":45,"ambition":72,"discipline":72,"majorLeagueServiceWeeks":12,"draftNum":0,"draftSeason":2019}
]
